Topsis_Jay/__init__.py
TOPSIS_Jay_101803206-0.6.dist-info/LICENSE.txt
TOPSIS_Jay_101803206-0.6.dist-info/METADATA
TOPSIS_Jay_101803206-0.6.dist-info/WHEEL
TOPSIS_Jay_101803206-0.6.dist-info/top_level.txt
TOPSIS_Jay_101803206-0.6.dist-info/RECORD
