Metadata-Version: 2.1
Name: TOPSIS-Jay-101803206
Version: 0.6
Summary: A Multiple Criteria Decision Making System using TOPSIS
Home-page: https://github.com/Jaisood08/TOPSIS-JAY-101803206
Author: Jay Sood
Author-email: jaisood08@gmail.com
License: MIT
Keywords: TOPSIS,101803206,JAY Sood,DS-ASSIGNMENT 6 
Platform: UNKNOWN
Classifier: Development Status :: 3 - Alpha
Classifier: Intended Audience :: Developers
Classifier: Topic :: Software Development :: Build Tools
Classifier: License :: OSI Approved :: MIT License
Classifier: Programming Language :: Python :: 3
Classifier: Programming Language :: Python :: 3.4
Classifier: Programming Language :: Python :: 3.5
Classifier: Programming Language :: Python :: 3.6
Requires-Dist: pandas
